modest/__init__.py
modest/modularfilter.py
modest/plots/__init__.py
modest/plots/chandraPlots.py
modest/plots/montecarloplots2.py
modest/plots/photonscatterplot.py
modest/setupfunctions/__init__.py
modest/setupfunctions/buildsignalmodels.py
modest/setupfunctions/buildsubstates.py
modest/setupfunctions/builduserdata.py
modest/setupfunctions/montecarlo.py
modest/signals/__init__.py
modest/signals/oneDimensionalObject.py
modest/signals/periodicxraysource.py
modest/signals/pointsource.py
modest/signals/poissonsource.py
modest/signals/signalsource.py
modest/signals/staticxraypointsource.py
modest/signals/uniformnoisexraysource.py
modest/signals/xraysource.py
modest/spacecraft/__init__.py
modest/spacecraft/chandra.py
modest/spacecraft/simulation.py
modest/substates/__init__.py
modest/substates/attitude.py
modest/substates/correlationvector.py
modest/substates/oneDimensionalPositionVelocity.py
modest/substates/substate.py
modest/utils/QuaternionHelperFunctions.py
modest/utils/__init__.py
modest/utils/accessPSC.py
modest/utils/covarianceUtils.py
modest/utils/loadPulsarData.py
modest/utils/mleTDOAEstimation.py
modest/utils/physicalconstants.py
modest/utils/spacegeometry.py
modest/utils/xrayphotons.py
modest-0.1a21.dist-info/LICENSE
modest-0.1a21.dist-info/METADATA
modest-0.1a21.dist-info/WHEEL
modest-0.1a21.dist-info/top_level.txt
modest-0.1a21.dist-info/RECORD
