Metadata-Version: 1.0
Name: modest
Version: 0.1a21
Summary: A modular estimation library
Home-page: https://modular-estimator.readthedocs.io/
Author: Joel Runnels
Author-email: runne010@umn.edu
License: MIT
Platform: UNKNOWN
